ytdebunk/__init__.py
ytdebunk/downloader.py
ytdebunk/philosopher.py
ytdebunk/refiner.py
ytdebunk/settings.py
ytdebunk/transcriber.py
ytdebunk/ytdebunk.py
ytdebunk-1.1.3.dist-info/licenses/LICENSE
ytdebunk-1.1.3.dist-info/METADATA
ytdebunk-1.1.3.dist-info/WHEEL
ytdebunk-1.1.3.dist-info/entry_points.txt
ytdebunk-1.1.3.dist-info/top_level.txt
ytdebunk-1.1.3.dist-info/RECORD
