Metadata-Version: 2.4
Name: ytdebunk
Version: 1.1.3
Summary: A CLI tool to automatically download audio .mp3 from a YouTube video link, transcribe it, refine and find logical errors in the transcription using AI.
Home-page: https://github.com/hissain/youtuber-debunked
Author: Md. Sazzad Hissain Khan
Author-email: hissain.khan@gmail.com
Keywords: youtube,transcription,audio,refinement,ai,bengali,geminai,librosa,streamlit
Classifier: Programming Language :: Python :: 3
Classifier: License :: OSI Approved :: MIT License
License-File: LICENSE
Requires-Dist: numpy<2
Requires-Dist: python-dotenv==1.0.1
Requires-Dist: google-generativeai==0.8.4
Requires-Dist: yt-dlp==2025.3.21
Requires-Dist: torch==2.1.0
Requires-Dist: torchaudio==2.1.0
Requires-Dist: librosa==0.11.0
Requires-Dist: transformers==4.36.2
Dynamic: author
Dynamic: author-email
Dynamic: classifier
Dynamic: description
Dynamic: description-content-type
Dynamic: home-page
Dynamic: keywords
Dynamic: license-file
Dynamic: requires-dist
Dynamic: summary
